apm_system/__init__.py
apm_system/apm_adapter.py
apm_system/apm_dialect.py
apm_system/db_engine_specs.py
system_superset_driver-0.0.18.dist-info/METADATA
system_superset_driver-0.0.18.dist-info/WHEEL
system_superset_driver-0.0.18.dist-info/entry_points.txt
system_superset_driver-0.0.18.dist-info/top_level.txt
system_superset_driver-0.0.18.dist-info/RECORD
