Metadata-Version: 2.1
Name: system-superset-driver
Version: 0.0.18
Summary: UNKNOWN
Home-page: UNKNOWN
License: UNKNOWN
Platform: UNKNOWN
Requires-Dist: shillelagh (>=1.0.6)
Requires-Dist: sqlalchemy (>=1.3.0)
Requires-Dist: requests (>=2.20.0)
Requires-Dist: psutil
Requires-Dist: typing-extensions
